prql_python-0.11.2.dist-info/METADATA
prql_python-0.11.2.dist-info/WHEEL
prql_python/__init__.py
prql_python/__init__.pyi
prql_python/py.typed
prql_python/prql_python.abi3.so
prql_python-0.11.2.dist-info/RECORD
