Metadata-Version: 2.1
Name: prql-python
Version: 0.11.2
Classifier: Programming Language :: Rust
Classifier: Programming Language :: Python :: Implementation :: CPython
Classifier: Programming Language :: Python :: Implementation :: PyPy
Requires-Dist: pytest >=7 ; extra == 'test'
Requires-Dist: mypy ==1.8.0 ; extra == 'test'
Provides-Extra: test
License: Apache-2.0
Requires-Python: >=3.8
Project-URL: Source Code, https://github.com/PRQL/prql
